{
  "market_intel": {
    "VIRTUAL": {
      "price": 0.7041,
      "price_24h_avg": 0.7041,
      "social_velocity": 1.0,
      "whale_alert": "None",
      "current_liquidity": {},
      "confidence_score": 1.0,
      "last_updated": "2026-03-10T18:16:35.011244+00:00"
    }
  },
  "strategic_intel": {
    "expected_pnet": 0.0,
    "risk_mitigation_plan": "Multi-Alpha Scan Active. Latest: ETH/USDT",
    "success_probability": 0.85,
    "strategy_id": "",
    "diplomatic_presets": {
      "execution_priority": "CRITICAL"
    },
    "active_opportunities": {
      "AIXBT/USDT": {
        "sharpe": 6.19,
        "confidence": "MEDIUM",
        "alert_level": "Critical",
        "last_detected": "2026-04-06T01:05:06"
      },
      "ETH/USDT": {
        "sharpe": 5.11,
        "confidence": "MEDIUM",
        "alert_level": "Warning",
        "last_detected": "2026-04-06T02:08:06"
      },
      "ETH": {
        "sharpe": 5.11,
        "confidence": "MEDIUM",
        "alert_level": "Warning",
        "last_detected": "2026-04-05T23:36:48"
      },
      "BTC": {
        "sharpe": 21.87,
        "confidence": "MEDIUM",
        "alert_level": "Warning",
        "last_detected": "2026-04-06T00:42:29"
      }
    },
    "opportunity_count": 4,
    "last_updated": "2026-04-06T02:08:06.826906+00:00"
  },
  "diplomacy_intel": {},
  "execution_history": [],
  "system_status": "ONLINE",
  "version": "5.2",
  "performance_summary": {
    "accuracy_score": 0.0,
    "total_evaluated_trades": 3,
    "recent_performance": [
      {
        "symbol": "VIRTUAL",
        "entry_price": 0.642896989204046,
        "exit_price": 0.608847797166124,
        "amount_usd": 4377.01,
        "pnl_pct": -5.3
      },
      {
        "symbol": "VIRTUAL",
        "entry_price": 0.635136308308466,
        "exit_price": 0.608847797166124,
        "amount_usd": 4373.23,
        "pnl_pct": -4.14
      },
      {
        "symbol": "VIRTUAL",
        "entry_price": 0.62875435526726,
        "exit_price": 0.608847797166124,
        "amount_usd": 2672.4,
        "pnl_pct": -3.17
      }
    ],
    "last_evaluated": "2026-04-06T02:09:54.295715"
  },
  "last_periodic_symbol": "AIXBT",
  "last_unified_council_ts": 1775439749.38188,
  "last_unified_council_symbol": "VIRTUAL"
}