{
  "market_intel": {
    "VIRTUAL": {
      "price": 0.7041,
      "price_24h_avg": 0.7041,
      "social_velocity": 1.0,
      "whale_alert": "None",
      "current_liquidity": {},
      "confidence_score": 1.0,
      "last_updated": "2026-03-10T18:16:35.011244+00:00"
    }
  },
  "strategic_intel": {
    "expected_pnet": 0.0,
    "risk_mitigation_plan": "Multi-Alpha Scan Active. Latest: VIRTUAL/USDT",
    "success_probability": 0.85,
    "strategy_id": "",
    "diplomatic_presets": {
      "execution_priority": "CRITICAL"
    },
    "active_opportunities": {
      "AIXBT/USDT": {
        "sharpe": 9.85,
        "confidence": "MEDIUM",
        "alert_level": "Critical",
        "last_detected": "2026-04-16T01:15:35"
      },
      "ETH/USDT": {
        "sharpe": 5.24,
        "confidence": "HIGH",
        "alert_level": "Critical",
        "last_detected": "2026-04-09T12:18:34"
      },
      "ETH": {
        "sharpe": 5.47,
        "confidence": "HIGH",
        "alert_level": "Warning",
        "last_detected": "2026-04-11T17:50:57"
      },
      "BTC": {
        "sharpe": 21.87,
        "confidence": "MEDIUM",
        "alert_level": "Warning",
        "last_detected": "2026-04-14T23:20:01"
      },
      "ROBO/USDT": {
        "sharpe": 17.37,
        "confidence": "MEDIUM",
        "alert_level": "Critical",
        "last_detected": "2026-04-15T01:15:58"
      },
      "VIRTUAL/USDT": {
        "sharpe": 11.91,
        "confidence": "MEDIUM",
        "alert_level": "Warning",
        "last_detected": "2026-04-17T03:00:26"
      },
      "VIRTUAL": {
        "sharpe": 11.91,
        "confidence": "MEDIUM",
        "alert_level": "Normal",
        "last_detected": "2026-04-17T02:06:45"
      },
      "TIBBIR/USDT": {
        "sharpe": 10.23,
        "confidence": "MEDIUM",
        "alert_level": "Critical",
        "last_detected": "2026-04-16T01:15:46"
      },
      "SOL/USDT": {
        "sharpe": 29.46,
        "confidence": "MEDIUM",
        "alert_level": "Critical",
        "last_detected": "2026-04-14T17:01:45"
      },
      "BNB/USDT": {
        "sharpe": 30.26,
        "confidence": "MEDIUM",
        "alert_level": "Normal",
        "last_detected": "2026-04-14T17:01:58"
      }
    },
    "opportunity_count": 10,
    "last_updated": "2026-04-17T03:00:26.022213+00:00"
  },
  "diplomacy_intel": {},
  "execution_history": [],
  "system_status": "ONLINE",
  "version": "5.2",
  "performance_summary": {
    "accuracy_score": 50.62,
    "total_evaluated_trades": 81,
    "tier0_accuracy": 43.59,
    "tier0_trades": 39,
    "tier1_accuracy": 57.14,
    "tier1_trades": 42,
    "open_positions_count": 5,
    "recent_performance": [
      {
        "symbol": "VIRTUAL",
        "entry_price": 0.692724228533208,
        "exit_price": 0.671090118951749,
        "amount_usd": 2623.25,
        "pnl_pct": -3.12,
        "sell_time": "2026-04-14T18:38:56.391197+00:00"
      },
      {
        "symbol": "VIRTUAL",
        "entry_price": 0.671326495909551,
        "exit_price": 0.700987230334744,
        "amount_usd": 4344.13,
        "pnl_pct": 4.42,
        "sell_time": "2026-04-16T03:54:39.026625+00:00"
      },
      {
        "symbol": "VIRTUAL",
        "entry_price": 0.670509,
        "exit_price": 0.700987230334744,
        "amount_usd": 862.71,
        "pnl_pct": 4.55,
        "sell_time": "2026-04-16T03:54:39.026625+00:00"
      },
      {
        "symbol": "VIRTUAL",
        "entry_price": 0.670509,
        "exit_price": 0.727639999483812,
        "amount_usd": 1742.26,
        "pnl_pct": 8.52,
        "sell_time": "2026-04-16T13:22:45.636284+00:00"
      },
      {
        "symbol": "VIRTUAL",
        "entry_price": 0.67371950299218,
        "exit_price": 0.727639999483812,
        "amount_usd": 3475.85,
        "pnl_pct": 8.0,
        "sell_time": "2026-04-16T13:22:45.636284+00:00"
      }
    ],
    "open_positions": [
      {
        "symbol": "BTC",
        "entry_price": 67156.79,
        "current_price": 74697.0,
        "amount_usd": 2634.14,
        "pnl_pct": 11.23
      },
      {
        "symbol": "BTC",
        "entry_price": 66645.97,
        "current_price": 74697.0,
        "amount_usd": 2737.81,
        "pnl_pct": 12.08
      },
      {
        "symbol": "BTC",
        "entry_price": 69317.44,
        "current_price": 74697.0,
        "amount_usd": 2636.09,
        "pnl_pct": 7.76
      },
      {
        "symbol": "ETH",
        "entry_price": 2325.07,
        "current_price": 2331.27,
        "amount_usd": 4363.54,
        "pnl_pct": 0.27
      },
      {
        "symbol": "ETH",
        "entry_price": 2333.47,
        "current_price": 2331.27,
        "amount_usd": 4370.62,
        "pnl_pct": -0.09
      }
    ],
    "advanced_metrics": {
      "sortino_ratio": 7.465,
      "max_drawdown": -0.26,
      "calmar_ratio": 27.096,
      "annual_return": 7.039,
      "omega_ratio": 1.807
    },
    "last_evaluated": "2026-04-17T03:01:43.320786"
  },
  "last_periodic_symbol": "AIXBT",
  "last_unified_council_ts": 1776391585.2872932,
  "last_unified_council_symbol": "VIRTUAL"
}