{
  "market_intel": {
    "VIRTUAL": {
      "price": 0.7041,
      "price_24h_avg": 0.7041,
      "social_velocity": 1.0,
      "whale_alert": "None",
      "current_liquidity": {},
      "confidence_score": 1.0,
      "last_updated": "2026-03-10T18:16:35.011244+00:00"
    }
  },
  "strategic_intel": {
    "expected_pnet": 0.0,
    "risk_mitigation_plan": "Multi-Alpha Scan Active. Latest: AVAX/USDT",
    "success_probability": 0.85,
    "strategy_id": "TEST_ANTI_NOISE",
    "diplomatic_presets": {
      "execution_priority": "CRITICAL"
    },
    "active_opportunities": {
      "ETH/USDT": {
        "sharpe": 5.2,
        "alert_level": "Critical",
        "last_detected": "2026-03-14T05:00:20"
      },
      "SOL/USDT": {
        "sharpe": 5.2,
        "alert_level": "Critical",
        "last_detected": "2026-03-14T05:00:28"
      },
      "ADA/USDT": {
        "sharpe": 5.2,
        "alert_level": "Normal",
        "last_detected": "2026-03-14T04:38:03"
      },
      "AVAX/USDT": {
        "sharpe": 6.2,
        "alert_level": "Warning",
        "last_detected": "2026-03-14T05:02:12"
      },
      "VIRTUAL/USDT": {
        "sharpe": 5.2,
        "alert_level": "Critical",
        "last_detected": "2026-03-14T04:59:52"
      },
      "AIXBT/USDT": {
        "sharpe": 5.1,
        "alert_level": "Critical",
        "last_detected": "2026-03-14T04:59:58"
      },
      "GAME/USDT": {
        "sharpe": 6.2,
        "alert_level": "Normal",
        "last_detected": "2026-03-14T05:00:06"
      }
    },
    "opportunity_count": 7,
    "last_updated": "2026-03-14T05:02:12.547591+00:00"
  },
  "diplomacy_intel": {},
  "execution_history": [],
  "system_status": "ONLINE",
  "version": "5.2",
  "performance_summary": {
    "accuracy_score": 0.0,
    "total_evaluated_trades": 0,
    "recent_performance": [],
    "last_evaluated": "2026-03-14T05:02:34.543318"
  }
}