{"status": "success", "symbol": "VIRTUAL", "name": "Virtual Protocol", "priceUsd": "0.7402", "priceChange": {"m5": 0.19, "h1": 0.36, "h6": 0.37, "h24": -3.88}, "volume": {"h24": 6255731.27, "h6": 946676.56, "h1": 164788.01, "m5": 16289.78}, "liquidity": {"usd": 867033.51, "base": 742561, "quote": 148.9595}, "url": "https://dexscreener.com/base/0x3f0296bf652e19bca772ec3df08b32732f93014a", "pairAddress": "0x3f0296BF652e19bca772EC3dF08b32732F93014A", "chainId": "base", "timestamp": 1772706213.0808961}